tinengine/Tin.ico
tinengine/TinEngine.cp39-win_amd64.pyd
tinengine/TinEngine.pyd
tinengine/__init__.py
tinengine/data/bin/HtmlShow.exe
tinengine/data/bin/Tkhtml30.dll
tinengine/data/bin/combobox-2.3.tm
tinengine/data/bin/combobox.tcl
tinengine/data/bin/pkgIndex.tcl
tinengine/data/img/tinlogo.png
tinengine-2.5.0.dist-info/LICENSE.txt
tinengine-2.5.0.dist-info/METADATA
tinengine-2.5.0.dist-info/WHEEL
tinengine-2.5.0.dist-info/top_level.txt
tinengine-2.5.0.dist-info/RECORD
